[
  {
    "id": "vibe-1716301200000",
    "text": "The creative templates were shared a bit too late for our last workshop presentation deck. Next time let's have a unified theme ready 1 week in advance.",
    "timestamp": "2026-05-18T14:20:00.000Z"
  },
  {
    "id": "vibe-1716387600000",
    "text": "Excited for the upcoming Build with AI hackathon! I hope we can offer vegetarian pizza options for Marcus' catering roster.",
    "timestamp": "2026-05-19T09:10:00.000Z"
  },
  {
    "id": "vibe-1716474000000",
    "text": "Communication across the Labs team and Creatives team was perfect this week. Love the shared Figma file approach!",
    "timestamp": "2026-05-20T11:45:00.000Z"
  }
]
